LICENSE.txt
MANIFEST.in
README.md
README.rst
requirements.txt
setup.py
requests_negotiate_sspi/__init__.py
requests_negotiate_sspi/requests_negotiate_sspi.py
requests_negotiate_sspi.egg-info/PKG-INFO
requests_negotiate_sspi.egg-info/SOURCES.txt
requests_negotiate_sspi.egg-info/dependency_links.txt
requests_negotiate_sspi.egg-info/requires.txt
requests_negotiate_sspi.egg-info/top_level.txt
requests_negotiate_sspi.egg-info/version.txt
requests_negotiate_sspi.egg-info/version_full.txt