Metadata-Version: 2.1
Name: requests-negotiate-sspi
Version: 0.4.5
Summary: This package allows for Single-Sign On HTTP Negotiate authentication using the requests library on Windows.
Home-page: https://github.com/brandond/requests-negotiate-sspi
Author: Brandon Davidson
Author-email: brad@oatmail.org
License: UNKNOWN
Platform: UNKNOWN
Classifier: Development Status :: 4 - Beta
Classifier: Environment :: Win32 (MS Windows)
Classifier: Intended Audience :: Developers
Classifier: License :: OSI Approved :: Apache Software License
Classifier: Programming Language :: Python :: 2
Classifier: Programming Language :: Python :: 2.7
Classifier: Programming Language :: Python :: 3
Classifier: Programming Language :: Python :: 3.4
Classifier: Programming Language :: Python :: 3.5
Classifier: Programming Language :: Python
Provides: requests_negotiate_sspi
Provides-Extra: dev
